opsf_package_spartajet/__init__.py
opsf_package_spartajet/splfltlin.py
opsf_package_spartajet-0.0.1.dist-info/METADATA
opsf_package_spartajet-0.0.1.dist-info/WHEEL
opsf_package_spartajet-0.0.1.dist-info/entry_points.txt
opsf_package_spartajet-0.0.1.dist-info/license_files/LICENSE
opsf_package_spartajet-0.0.1.dist-info/RECORD
