Metadata-Version: 2.1
Name: opsf-package-spartajet
Version: 0.0.1
Summary: ISO/TS 16610-22 Open profile spline filter, refer to https://ww2.mathworks.cn/matlabcentral/fileexchange/52562-surface-metrology-open-profile-spline-filter?s_tid=srchtitle
Project-URL: Bug Tracker, https://github.com/spartajet/opsf/issues
Project-URL: Homepage, https://github.com/spartajet/opsf
Author-email: Xiaozhong Guo <guoxiaozhong@zstu.edu.cn>
License: MIT License
Classifier: License :: OSI Approved :: MIT License
Classifier: Operating System :: OS Independent
Classifier: Programming Language :: Python :: 3
Requires-Python: >=3.7
